dingdinghelper/__init__.py
dingdinghelper/dingdinghelper.py
dingdinghelper/ws.py
dingdinghelper/websocket/__init__.py
dingdinghelper/websocket/_abnf.py
dingdinghelper/websocket/_app.py
dingdinghelper/websocket/_cookiejar.py
dingdinghelper/websocket/_core.py
dingdinghelper/websocket/_exceptions.py
dingdinghelper/websocket/_handshake.py
dingdinghelper/websocket/_http.py
dingdinghelper/websocket/_logging.py
dingdinghelper/websocket/_socket.py
dingdinghelper/websocket/_ssl_compat.py
dingdinghelper/websocket/_url.py
dingdinghelper/websocket/_utils.py
dingdinghelper-0.0.5.dist-info/LICENSE
dingdinghelper-0.0.5.dist-info/METADATA
dingdinghelper-0.0.5.dist-info/WHEEL
dingdinghelper-0.0.5.dist-info/top_level.txt
dingdinghelper-0.0.5.dist-info/RECORD
