Metadata-Version: 2.1
Name: dingdinghelper
Version: 0.0.5
Summary: DingDing Helper.
Home-page: https://github.com/l2m2/dingding-helper
Author: l2m2
Author-email: l2m2lq@gmail.com
License: UNKNOWN
Platform: UNKNOWN
Classifier: Programming Language :: Python :: 3
Classifier: License :: OSI Approved :: MIT License
Classifier: Operating System :: OS Independent
Requires-Python: >=3.6
